s4B.v
module s4B(clk,clr,a,e);
input clk,clr,a;
output reg e;
reg b,c,d;

always @(posedge clk or negedge clr) begin
    if(!clr)begin ;b<=0;c<=0;d<=0;e<=0; end

    else  begin
        e<=d;
        d<=c;
        c<=b;
        b<=a;
    end

    
end
endmodule

s4b_tb.v

`timescale 1ns/1ps
`include "s4B.v"
module s4b_tb;
reg clk,clr,A;
wire E;

s4B dut(.clk(clk),.clr(clr),.a(A),.e(E));

initial begin
    clk=1'b0;
    #2 clr=1'b0;
    #5 clr=1'b1;

end
always #5 clk=~clk;
initial begin 
    
    
    repeat(2) begin
        #10 A<=0;
        #10 A<=0;
        #10 A<=1;
        #10 A<=1;
    end
  
  
end
initial begin
    $dumpfile("s4b_tb.vcd");
    $dumpvars(0,s4b_tb);

    #200 $finish;
end

endmodule

s4b_tb.vcd
$date
	Sat Aug 16 19:05:10 2025
$end
$version
	Icarus Verilog
$end
$timescale
	1ps
$end
$scope module s4b_tb $end
$var wire 1 ! E $end
$var reg 1 " A $end
$var reg 1 # clk $end
$var reg 1 $ clr $end
$scope module dut $end
$var wire 1 " a $end
$var wire 1 # clk $end
$var wire 1 $ clr $end
$var reg 1 % b $end
$var reg 1 & c $end
$var reg 1 ' d $end
$var reg 1 ! e $end
$upscope $end
$upscope $end
$enddefinitions $end
$comment Show the parameter values. $end
$dumpall
$end
#0
$dumpvars
x'
x&
x%
x$
0#
x"
x!
$end
#2000
0!
0'
0&
0%
0$
#5000
1#
#7000
1$
#10000
0"
0#
#15000
1#
#20000
0#
#25000
1#
#30000
1"
0#
#35000
1%
1#
#40000
0#
#45000
1&
1#
#50000
0"
0#
#55000
0%
1'
1#
#60000
0#
#65000
0&
1!
1#
#70000
1"
0#
#75000
1%
0'
1#
#80000
0#
#85000
1&
0!
1#
#90000
0#
#95000
1'
1#
#100000
0#
#105000
1!
1#
