sequence_detector.v
//***********SEQUENCE DETECTING***********
//_____FSM mealy method
//___Design Of a sequence detector.
//A circuit accepts a serial bit stream "x" as input and produces a serial bit stream " zr• as output.
//Whenever the bit pattern "0110" appears in the input stream, it outputs z = 1; at all other times, z = O.
//Overlapping occurrences of the pattern are also detected.
//This is a Mealy Machine.

module sdt(x,clk,reset,z);
input x,clk,reset;
output reg z;
parameter s0=0,s1=1,s2=2,s3=3;
reg[0:1] ps,ns;

always @(posedge clk or posedge reset) 
    if(reset) ps<=s0;
    else      ps<=ns;

always @(ps,x) begin
    case(ps)
    s0:begin
        z=x?0:0;
        ns=x?s0:s1;
    end
    s1:begin
        z=x?0:0;
        ns=x?s2:s1;
    end
    s2:begin
        z=x?0:0;
        ns=x?s3:s1;
    end
    s3:begin
        z=x?0:1;
        ns=x?s0:s1;
    end
endcase
end

endmodule

sequence_detector_tb.v
`timescale 1ns / 1ps
`include "sequence_detector.v"

module ts;
reg clk,x,reset;
wire z;
sdt DUT(x,clk,reset,z);

initial begin
    $dumpfile("sdt.vcd"); $dumpvars(0,ts);
    clk=1'b0;
    reset=1'b1;
    #15 reset=1'b0;
end
always #5 clk=~clk;
initial
   begin
    #12 x=0; #10 x=0; #10 x=1; #10 x=1;
    #10 x=0; #10 x=1; #10 x=1; #10 x=0;
    #10 x=0; #10 x=1; #10 x=1; #10 x=0;
    #10 $finish;
   end
endmodule

sdt.vcd
$date
	Tue Jun 10 11:39:07 2025
$end
$version
	Icarus Verilog
$end
$timescale
	1ps
$end
$scope module ts $end
$var wire 1 ! z $end
$var reg 1 " clk $end
$var reg 1 # reset $end
$var reg 1 $ x $end
$scope module DUT $end
$var wire 1 " clk $end
$var wire 1 # reset $end
$var wire 1 $ x $end
$var parameter 32 % s0 $end
$var parameter 32 & s1 $end
$var parameter 32 ' s2 $end
$var parameter 32 ( s3 $end
$var reg 2 ) ns [0:1] $end
$var reg 2 * ps [0:1] $end
$var reg 1 ! z $end
$upscope $end
$upscope $end
$enddefinitions $end
$comment Show the parameter values. $end
$dumpall
b11 (
b10 '
b1 &
b0 %
$end
#0
$dumpvars
b0 *
b0x )
x$
1#
0"
0!
$end
#5000
1"
#10000
0"
#12000
b1 )
0$
#15000
b1 *
1"
0#
#20000
0"
#25000
1"
#30000
0"
#32000
b10 )
1$
#35000
b11 )
b10 *
1"
#40000
0"
#45000
b0 )
b11 *
1"
#50000
0"
#52000
b1 )
1!
0$
#55000
0!
b1 *
1"
#60000
0"
#62000
b10 )
1$
#65000
b11 )
b10 *
1"
#70000
0"
#75000
b0 )
b11 *
1"
#80000
0"
#82000
b1 )
1!
0$
#85000
0!
b1 *
1"
#90000
0"
#95000
1"
#100000
0"
#102000
b10 )
1$
#105000
b11 )
b10 *
1"
#110000
0"
#115000
b0 )
b11 *
1"
#120000
0"
#122000
b1 )
1!
0$
#125000
0!
b1 *
1"
