up_counter.v
module Counter(clear,clock,count);
   parameter N =7 ;
   input clear,clock;
   output reg[0:N] count;

   always @(negedge clock) begin
    if(clear)
    count<=0;
    else
     count<=count+1;
   end
endmodule

up_counter_tb.v
`timescale 1ns / 1ps
`include "up_counter.v"

module test_counter;
  reg clear,clock; wire [0:7] count;

Counter DUT (.clear(clear),.clock(clock),.count(count));

initial
begin
    clock=1'b0;
end
always #5 clock=~clock;

initial
  begin
    clear=1'b1;
    #15 clear=1'b0;
    #200 clear=1'b1;
    #10 $finish;
  end
initial
  begin
    $dumpfile("up_counter.vcd");
    $dumpvars(0,test_counter);
    $monitor($time  ,"  count:%d",count);
  end
endmodule

up_counter.vcd
$date
	Sun Jun 08 15:31:15 2025
$end
$version
	Icarus Verilog
$end
$timescale
	1ps
$end
$scope module test_counter $end
$var wire 8 ! count [0:7] $end
$var reg 1 " clear $end
$var reg 1 # clock $end
$scope module DUT $end
$var wire 1 " clear $end
$var wire 1 # clock $end
$var parameter 32 $ N $end
$var reg 8 % count [0:7] $end
$upscope $end
$upscope $end
$enddefinitions $end
$comment Show the parameter values. $end
$dumpall
b111 $
$end
#0
$dumpvars
b0 %
0#
1"
b0 !
$end
#5000
1#
#10000
0#
#15000
1#
0"
#20000
b1 !
b1 %
0#
#25000
1#
#30000
b10 !
b10 %
0#
#35000
1#
#40000
b11 !
b11 %
0#
#45000
1#
#50000
b100 !
b100 %
0#
#55000
1#
#60000
b101 !
b101 %
0#
#65000
1#
#70000
b110 !
b110 %
0#
#75000
1#
#80000
b111 !
b111 %
0#
#85000
1#
#90000
b1000 !
b1000 %
0#
#95000
1#
#100000
b1001 !
b1001 %
0#
#105000
1#
#110000
b1010 !
b1010 %
0#
#115000
1#
#120000
b1011 !
b1011 %
0#
#125000
1#
#130000
b1100 !
b1100 %
0#
#135000
1#
#140000
b1101 !
b1101 %
0#
#145000
1#
#150000
b1110 !
b1110 %
0#
#155000
1#
#160000
b1111 !
b1111 %
0#
#165000
1#
#170000
b10000 !
b10000 %
0#
#175000
1#
#180000
b10001 !
b10001 %
0#
#185000
1#
#190000
b10010 !
b10010 %
0#
#195000
1#
#200000
b10011 !
b10011 %
0#
#205000
1#
#210000
b10100 !
b10100 %
0#
#215000
1#
1"
#220000
b0 !
b0 %
0#
